usbmon/__init__.py
usbmon/addresses.py
usbmon/capture_session.py
usbmon/chatter.py
usbmon/constants.py
usbmon/descriptors.py
usbmon/packet.py
usbmon/pcapng.py
usbmon/py.typed
usbmon/setup.py
usbmon/capture/__init__.py
usbmon/capture/py.typed
usbmon/capture/usbmon_mmap.py
usbmon/capture/usbpcap.py
usbmon/support/__init__.py
usbmon/support/cp210x.py
usbmon/support/cp2110.py
usbmon/support/hid.py
usbmon/support/py.typed
usbmon/tools/__init__.py
usbmon/tools/_utils.py
usbmon/tools/capture_stats.py
usbmon/tools/chatter_cp210x.py
usbmon/tools/chatter_cp2110.py
usbmon/tools/chatter_hid.py
usbmon/tools/pcapng2base64.py
usbmon/tools/pcapng2text.py
usbmon/tools/py.typed
usbmon_tools-3.0.0.dist-info/AUTHORS
usbmon_tools-3.0.0.dist-info/Apache-2.0.txt
usbmon_tools-3.0.0.dist-info/CONTRIBUTING.md
usbmon_tools-3.0.0.dist-info/LICENSE
usbmon_tools-3.0.0.dist-info/METADATA
usbmon_tools-3.0.0.dist-info/MIT.txt
usbmon_tools-3.0.0.dist-info/Unlicense.txt
usbmon_tools-3.0.0.dist-info/WHEEL
usbmon_tools-3.0.0.dist-info/entry_points.txt
usbmon_tools-3.0.0.dist-info/top_level.txt
usbmon_tools-3.0.0.dist-info/RECORD
