Metadata-Version: 2.1
Name: usbmon-tools
Version: 3.0.0
Summary: usbmon processing utilities (for Linux and Windows captures).
Home-page: UNKNOWN
Author: Diego Elio Pettenò
Author-email: flameeyes@flameeyes.com
License: Apache-2.0
Platform: UNKNOWN
Classifier: Development Status :: 4 - Beta
Classifier: Environment :: Console
Classifier: Intended Audience :: Developers
Classifier: License :: OSI Approved :: Apache Software License
Classifier: Operating System :: OS Independent
Classifier: Programming Language :: Python
Classifier: Programming Language :: Python :: 3
Classifier: Topic :: System :: Hardware
Requires-Python: ~=3.7
Requires-Dist: click
Requires-Dist: construct (>=2.9)
Requires-Dist: hexdump
Requires-Dist: python-pcapng (>=1.0)
Provides-Extra: dev
Requires-Dist: absl-py ; extra == 'dev'
Requires-Dist: mypy ; extra == 'dev'
Requires-Dist: pre-commit ; extra == 'dev'
Requires-Dist: pytest (>=3.6.0) ; extra == 'dev'
Requires-Dist: pytest-mypy ; extra == 'dev'
Requires-Dist: pytest-timeout (>=1.3.0) ; extra == 'dev'
Requires-Dist: setuptools-scm ; extra == 'dev'
